myapp/__init__.py
myapp/myapp.py
yoshi-0.0.1.dist-info/LICENSE
yoshi-0.0.1.dist-info/METADATA
yoshi-0.0.1.dist-info/WHEEL
yoshi-0.0.1.dist-info/entry_points.txt
yoshi-0.0.1.dist-info/top_level.txt
yoshi-0.0.1.dist-info/RECORD
