Metadata-Version: 2.1
Name: yoshi
Version: 0.0.1
Summary: my first app for pypi
Home-page: https://github.com/liLy-1905/myapp
Author: Yoshimasa Yuri
Author-email: yurimore.tm@gmail.com
License: MIT License        
Platform: UNKNOWN
License-File: LICENSE
